{
    "context_hate": [
        {
            "eval_loss": 0.08066771924495697,
            "eval_calls_f1": 0.6690017513134852,
            "eval_women_f1": 0.4197530864197531,
            "eval_lgbti_f1": 0.4636871508379888,
            "eval_racism_f1": 0.6848249027237354,
            "eval_class_f1": 0.5074626865671642,
            "eval_politics_f1": 0.6262626262626262,
            "eval_disabled_f1": 0.5298013245033113,
            "eval_appearance_f1": 0.7329192546583851,
            "eval_criminal_f1": 0.6294706723891274,
            "eval_mean_f1": 0.5847981572151184,
            "eval_mean_precision": 0.5886422991752625,
            "eval_mean_recall": 0.5888310670852661,
            "eval_hate_precision": 0.6822945394373966,
            "eval_hate_recall": 0.6883695047301057,
            "eval_hate_f1": 0.6853185595567868,
            "eval_runtime": 33.6736,
            "eval_samples_per_second": 336.851,
            "eval_steps_per_second": 21.055
        },
        {
            "eval_loss": 0.07805836945772171,
            "eval_calls_f1": 0.6820603907637655,
            "eval_women_f1": 0.42561983471074377,
            "eval_lgbti_f1": 0.44886363636363635,
            "eval_racism_f1": 0.7009249743062692,
            "eval_class_f1": 0.5217391304347826,
            "eval_politics_f1": 0.6222961730449251,
            "eval_disabled_f1": 0.5492957746478874,
            "eval_appearance_f1": 0.7311557788944724,
            "eval_criminal_f1": 0.6409155937052932,
            "eval_mean_f1": 0.5914301872253418,
            "eval_mean_precision": 0.6017844676971436,
            "eval_mean_recall": 0.5864918828010559,
            "eval_hate_precision": 0.6966420034149118,
            "eval_hate_recall": 0.6811352253756261,
            "eval_hate_f1": 0.6888013505908835,
            "eval_runtime": 34.0112,
            "eval_samples_per_second": 333.507,
            "eval_steps_per_second": 20.846
        },
        {
            "eval_loss": 0.08100133389234543,
            "eval_calls_f1": 0.6863084922010398,
            "eval_women_f1": 0.4271457085828343,
            "eval_lgbti_f1": 0.4628571428571429,
            "eval_racism_f1": 0.6786427145708582,
            "eval_class_f1": 0.5179856115107914,
            "eval_politics_f1": 0.5862068965517242,
            "eval_disabled_f1": 0.5547445255474454,
            "eval_appearance_f1": 0.7265822784810128,
            "eval_criminal_f1": 0.64,
            "eval_mean_f1": 0.586719274520874,
            "eval_mean_precision": 0.5954419374465942,
            "eval_mean_recall": 0.5820140838623047,
            "eval_hate_precision": 0.6870056497175141,
            "eval_hate_recall": 0.6766833611574847,
            "eval_hate_f1": 0.6818054387440426,
            "eval_runtime": 34.0703,
            "eval_samples_per_second": 332.929,
            "eval_steps_per_second": 20.81
        },
        {
            "eval_loss": 0.08015943318605423,
            "eval_calls_f1": 0.6738351254480287,
            "eval_women_f1": 0.3947939262472885,
            "eval_lgbti_f1": 0.4540229885057471,
            "eval_racism_f1": 0.6834170854271356,
            "eval_class_f1": 0.524822695035461,
            "eval_politics_f1": 0.6254180602006689,
            "eval_disabled_f1": 0.56,
            "eval_appearance_f1": 0.7461538461538462,
            "eval_criminal_f1": 0.6274509803921567,
            "eval_mean_f1": 0.5877683162689209,
            "eval_mean_precision": 0.6010110378265381,
            "eval_mean_recall": 0.5803951025009155,
            "eval_hate_precision": 0.6977011494252874,
            "eval_hate_recall": 0.6755703951029494,
            "eval_hate_f1": 0.6864574498162285,
            "eval_runtime": 34.1842,
            "eval_samples_per_second": 331.82,
            "eval_steps_per_second": 20.741
        },
        {
            "eval_loss": 0.08054208755493164,
            "eval_calls_f1": 0.6499102333931778,
            "eval_women_f1": 0.41613588110403404,
            "eval_lgbti_f1": 0.471264367816092,
            "eval_racism_f1": 0.6862944162436548,
            "eval_class_f1": 0.5069444444444444,
            "eval_politics_f1": 0.6245847176079734,
            "eval_disabled_f1": 0.5543859649122808,
            "eval_appearance_f1": 0.7355163727959697,
            "eval_criminal_f1": 0.6322930800542741,
            "eval_mean_f1": 0.5863699316978455,
            "eval_mean_precision": 0.5923664569854736,
            "eval_mean_recall": 0.5861719846725464,
            "eval_hate_precision": 0.6852367688022284,
            "eval_hate_recall": 0.6844741235392321,
            "eval_hate_f1": 0.6848552338530067,
            "eval_runtime": 34.2561,
            "eval_samples_per_second": 331.124,
            "eval_steps_per_second": 20.697
        },
        {
            "eval_loss": 0.0799243152141571,
            "eval_calls_f1": 0.6852173913043479,
            "eval_women_f1": 0.4264392324093817,
            "eval_lgbti_f1": 0.4405797101449275,
            "eval_racism_f1": 0.6746268656716417,
            "eval_class_f1": 0.49640287769784175,
            "eval_politics_f1": 0.6298157453936349,
            "eval_disabled_f1": 0.5405405405405406,
            "eval_appearance_f1": 0.7224242424242423,
            "eval_criminal_f1": 0.6248216833095578,
            "eval_mean_f1": 0.5823187232017517,
            "eval_mean_precision": 0.5877184867858887,
            "eval_mean_recall": 0.5854833126068115,
            "eval_hate_precision": 0.6852678571428571,
            "eval_hate_recall": 0.6833611574846967,
            "eval_hate_f1": 0.6843131791585401,
            "eval_runtime": 33.962,
            "eval_samples_per_second": 333.991,
            "eval_steps_per_second": 20.876
        },
        {
            "eval_loss": 0.07916750758886337,
            "eval_calls_f1": 0.6423357664233577,
            "eval_women_f1": 0.42561983471074377,
            "eval_lgbti_f1": 0.5154061624649859,
            "eval_racism_f1": 0.7067510548523208,
            "eval_class_f1": 0.5168539325842696,
            "eval_politics_f1": 0.6234676007005254,
            "eval_disabled_f1": 0.5579710144927535,
            "eval_appearance_f1": 0.7229813664596273,
            "eval_criminal_f1": 0.6431478968792401,
            "eval_mean_f1": 0.5949482917785645,
            "eval_mean_precision": 0.612044095993042,
            "eval_mean_recall": 0.5837054252624512,
            "eval_hate_precision": 0.6966610073571025,
            "eval_hate_recall": 0.6850306065664997,
            "eval_hate_f1": 0.6907968574635241,
            "eval_runtime": 34.1867,
            "eval_samples_per_second": 331.795,
            "eval_steps_per_second": 20.739
        },
        {
            "eval_loss": 0.0809900239109993,
            "eval_calls_f1": 0.6581818181818182,
            "eval_women_f1": 0.4309623430962343,
            "eval_lgbti_f1": 0.5027624309392265,
            "eval_racism_f1": 0.6720977596741345,
            "eval_class_f1": 0.4755244755244755,
            "eval_politics_f1": 0.6288492706645057,
            "eval_disabled_f1": 0.5306122448979591,
            "eval_appearance_f1": 0.7078787878787879,
            "eval_criminal_f1": 0.647887323943662,
            "eval_mean_f1": 0.5838617086410522,
            "eval_mean_precision": 0.5857131481170654,
            "eval_mean_recall": 0.5883395671844482,
            "eval_hate_precision": 0.6884422110552764,
            "eval_hate_recall": 0.6861435726210351,
            "eval_hate_f1": 0.6872909698996655,
            "eval_runtime": 34.1494,
            "eval_samples_per_second": 332.158,
            "eval_steps_per_second": 20.762
        },
        {
            "eval_loss": 0.07755869626998901,
            "eval_calls_f1": 0.674955595026643,
            "eval_women_f1": 0.41478439425051333,
            "eval_lgbti_f1": 0.4615384615384616,
            "eval_racism_f1": 0.6836935166994106,
            "eval_class_f1": 0.47750865051903113,
            "eval_politics_f1": 0.6141215106732348,
            "eval_disabled_f1": 0.537878787878788,
            "eval_appearance_f1": 0.7261306532663316,
            "eval_criminal_f1": 0.6602475928473176,
            "eval_mean_f1": 0.5834288001060486,
            "eval_mean_precision": 0.5869576930999756,
            "eval_mean_recall": 0.5837180614471436,
            "eval_hate_precision": 0.6915836101882613,
            "eval_hate_recall": 0.6950473010573177,
            "eval_hate_f1": 0.6933111296142103,
            "eval_runtime": 34.1739,
            "eval_samples_per_second": 331.92,
            "eval_steps_per_second": 20.747
        },
        {
            "eval_loss": 0.07872223109006882,
            "eval_calls_f1": 0.6842105263157895,
            "eval_women_f1": 0.417004048582996,
            "eval_lgbti_f1": 0.45454545454545453,
            "eval_racism_f1": 0.6811881188118812,
            "eval_class_f1": 0.5187713310580204,
            "eval_politics_f1": 0.6247933884297521,
            "eval_disabled_f1": 0.5684210526315789,
            "eval_appearance_f1": 0.7284105131414267,
            "eval_criminal_f1": 0.6684856753069577,
            "eval_mean_f1": 0.593981146812439,
            "eval_mean_precision": 0.5906030535697937,
            "eval_mean_recall": 0.6016676425933838,
            "eval_hate_precision": 0.6888646288209607,
            "eval_hate_recall": 0.7022815804117974,
            "eval_hate_f1": 0.6955084045191512,
            "eval_runtime": 34.284,
            "eval_samples_per_second": 330.854,
            "eval_steps_per_second": 20.68
        },
        {
            "eval_loss": 0.07954036444425583,
            "eval_calls_f1": 0.6631578947368422,
            "eval_women_f1": 0.42505592841163303,
            "eval_lgbti_f1": 0.47953216374269003,
            "eval_racism_f1": 0.6824742268041237,
            "eval_class_f1": 0.494296577946768,
            "eval_politics_f1": 0.6203208556149733,
            "eval_disabled_f1": 0.5409252669039145,
            "eval_appearance_f1": 0.731457800511509,
            "eval_criminal_f1": 0.6314285714285715,
            "eval_mean_f1": 0.5854054689407349,
            "eval_mean_precision": 0.6141921877861023,
            "eval_mean_recall": 0.5672364234924316,
            "eval_hate_precision": 0.7063679245283019,
            "eval_hate_recall": 0.6666666666666666,
            "eval_hate_f1": 0.6859433152018322,
            "eval_runtime": 32.8978,
            "eval_samples_per_second": 344.795,
            "eval_steps_per_second": 21.552
        },
        {
            "eval_loss": 0.07805836945772171,
            "eval_calls_f1": 0.6820603907637655,
            "eval_women_f1": 0.42561983471074377,
            "eval_lgbti_f1": 0.44886363636363635,
            "eval_racism_f1": 0.7009249743062692,
            "eval_class_f1": 0.5217391304347826,
            "eval_politics_f1": 0.6222961730449251,
            "eval_disabled_f1": 0.5492957746478874,
            "eval_appearance_f1": 0.7311557788944724,
            "eval_criminal_f1": 0.6409155937052932,
            "eval_mean_f1": 0.5914301872253418,
            "eval_mean_precision": 0.6017844676971436,
            "eval_mean_recall": 0.5864918828010559,
            "eval_hate_precision": 0.6966420034149118,
            "eval_hate_recall": 0.6811352253756261,
            "eval_hate_f1": 0.6888013505908835,
            "eval_runtime": 32.812,
            "eval_samples_per_second": 345.696,
            "eval_steps_per_second": 21.608
        },
        {
            "eval_loss": 0.08100133389234543,
            "eval_calls_f1": 0.6863084922010398,
            "eval_women_f1": 0.4271457085828343,
            "eval_lgbti_f1": 0.4628571428571429,
            "eval_racism_f1": 0.6786427145708582,
            "eval_class_f1": 0.5179856115107914,
            "eval_politics_f1": 0.5862068965517242,
            "eval_disabled_f1": 0.5547445255474454,
            "eval_appearance_f1": 0.7265822784810128,
            "eval_criminal_f1": 0.64,
            "eval_mean_f1": 0.586719274520874,
            "eval_mean_precision": 0.5954419374465942,
            "eval_mean_recall": 0.5820140838623047,
            "eval_hate_precision": 0.6870056497175141,
            "eval_hate_recall": 0.6766833611574847,
            "eval_hate_f1": 0.6818054387440426,
            "eval_runtime": 32.8546,
            "eval_samples_per_second": 345.248,
            "eval_steps_per_second": 21.58
        },
        {
            "eval_loss": 0.08015943318605423,
            "eval_calls_f1": 0.6738351254480287,
            "eval_women_f1": 0.3947939262472885,
            "eval_lgbti_f1": 0.4540229885057471,
            "eval_racism_f1": 0.6834170854271356,
            "eval_class_f1": 0.524822695035461,
            "eval_politics_f1": 0.6254180602006689,
            "eval_disabled_f1": 0.56,
            "eval_appearance_f1": 0.7461538461538462,
            "eval_criminal_f1": 0.6274509803921567,
            "eval_mean_f1": 0.5877683162689209,
            "eval_mean_precision": 0.6010110378265381,
            "eval_mean_recall": 0.5803951025009155,
            "eval_hate_precision": 0.6977011494252874,
            "eval_hate_recall": 0.6755703951029494,
            "eval_hate_f1": 0.6864574498162285,
            "eval_runtime": 32.8888,
            "eval_samples_per_second": 344.89,
            "eval_steps_per_second": 21.557
        },
        {
            "eval_loss": 0.08054208755493164,
            "eval_calls_f1": 0.6499102333931778,
            "eval_women_f1": 0.41613588110403404,
            "eval_lgbti_f1": 0.471264367816092,
            "eval_racism_f1": 0.6862944162436548,
            "eval_class_f1": 0.5069444444444444,
            "eval_politics_f1": 0.6245847176079734,
            "eval_disabled_f1": 0.5543859649122808,
            "eval_appearance_f1": 0.7355163727959697,
            "eval_criminal_f1": 0.6322930800542741,
            "eval_mean_f1": 0.5863699316978455,
            "eval_mean_precision": 0.5923664569854736,
            "eval_mean_recall": 0.5861719846725464,
            "eval_hate_precision": 0.6852367688022284,
            "eval_hate_recall": 0.6844741235392321,
            "eval_hate_f1": 0.6848552338530067,
            "eval_runtime": 32.8545,
            "eval_samples_per_second": 345.249,
            "eval_steps_per_second": 21.58
        }
    ],
    "hate": [
        {
            "eval_loss": 1.0987122058868408,
            "eval_ok_f1": 0.8252911813643926,
            "eval_ok_precision": 0.8621089223638471,
            "eval_ok_recall": 0.7914893617021277,
            "eval_hateful_f1": 0.7745168217609163,
            "eval_hateful_precision": 0.7340569877883311,
            "eval_hateful_recall": 0.8196969696969697,
            "eval_micro_f1": 0.803125,
            "eval_macro_f1": 0.7999039888381958,
            "eval_macro_precision": 0.7980829477310181,
            "eval_macro_recall": 0.8055931329727173,
            "eval_acc": 0.803125,
            "eval_runtime": 3.3049,
            "eval_samples_per_second": 484.124,
            "eval_steps_per_second": 30.258,
            "epoch": 5.0
        },
        {
            "eval_loss": 1.0800789594650269,
            "eval_ok_f1": 0.8011494252873562,
            "eval_ok_precision": 0.87125,
            "eval_ok_recall": 0.7414893617021276,
            "eval_hateful_f1": 0.7630136986301371,
            "eval_hateful_precision": 0.69625,
            "eval_hateful_recall": 0.843939393939394,
            "eval_micro_f1": 0.78375,
            "eval_macro_f1": 0.7820816040039062,
            "eval_macro_precision": 0.7837499976158142,
            "eval_macro_recall": 0.7927143573760986,
            "eval_acc": 0.78375,
            "eval_runtime": 3.1192,
            "eval_samples_per_second": 512.955,
            "eval_steps_per_second": 32.06,
            "epoch": 5.0
        },
        {
            "eval_loss": 1.1979527473449707,
            "eval_ok_f1": 0.7849588719153937,
            "eval_ok_precision": 0.8766404199475065,
            "eval_ok_recall": 0.7106382978723405,
            "eval_hateful_f1": 0.7556742323097464,
            "eval_hateful_precision": 0.6754176610978521,
            "eval_hateful_recall": 0.8575757575757575,
            "eval_micro_f1": 0.77125,
            "eval_macro_f1": 0.7703166007995605,
            "eval_macro_precision": 0.7760290503501892,
            "eval_macro_recall": 0.7841070294380188,
            "eval_acc": 0.77125,
            "eval_runtime": 3.0602,
            "eval_samples_per_second": 522.838,
            "eval_steps_per_second": 32.677,
            "epoch": 5.0
        },
        {
            "eval_loss": 1.103371262550354,
            "eval_ok_f1": 0.8050028425241615,
            "eval_ok_precision": 0.8644688644688645,
            "eval_ok_recall": 0.7531914893617021,
            "eval_hateful_f1": 0.761970853573907,
            "eval_hateful_precision": 0.7029449423815621,
            "eval_hateful_recall": 0.8318181818181818,
            "eval_micro_f1": 0.7856250000000001,
            "eval_macro_f1": 0.7834868431091309,
            "eval_macro_precision": 0.7837069034576416,
            "eval_macro_recall": 0.7925047874450684,
            "eval_acc": 0.785625,
            "eval_runtime": 3.2316,
            "eval_samples_per_second": 495.118,
            "eval_steps_per_second": 30.945,
            "epoch": 5.0
        },
        {
            "eval_loss": 0.5740035772323608,
            "eval_ok_f1": 0.8166761850371216,
            "eval_ok_precision": 0.8816276202219482,
            "eval_ok_recall": 0.7606382978723404,
            "eval_hateful_f1": 0.7784679089026916,
            "eval_hateful_precision": 0.714828897338403,
            "eval_hateful_recall": 0.8545454545454545,
            "eval_micro_f1": 0.799375,
            "eval_macro_f1": 0.7975720167160034,
            "eval_macro_precision": 0.7982282638549805,
            "eval_macro_recall": 0.8075919151306152,
            "eval_acc": 0.799375,
            "eval_runtime": 3.3677,
            "eval_samples_per_second": 475.097,
            "eval_steps_per_second": 29.694,
            "epoch": 5.0
        },
        {
            "eval_loss": 0.6837066411972046,
            "eval_ok_f1": 0.7793764988009594,
            "eval_ok_precision": 0.8928571428571429,
            "eval_ok_recall": 0.6914893617021277,
            "eval_hateful_f1": 0.7597911227154048,
            "eval_hateful_precision": 0.6674311926605505,
            "eval_hateful_recall": 0.8818181818181818,
            "eval_micro_f1": 0.7699999999999999,
            "eval_macro_f1": 0.7695838212966919,
            "eval_macro_precision": 0.7801441550254822,
            "eval_macro_recall": 0.7866537570953369,
            "eval_acc": 0.77,
            "eval_runtime": 3.1539,
            "eval_samples_per_second": 507.315,
            "eval_steps_per_second": 31.707,
            "epoch": 5.0
        },
        {
            "eval_loss": 1.2898576259613037,
            "eval_ok_f1": 0.7960716348931253,
            "eval_ok_precision": 0.8710493046776233,
            "eval_ok_recall": 0.7329787234042553,
            "eval_hateful_f1": 0.7597004765146359,
            "eval_hateful_precision": 0.6897404202719407,
            "eval_hateful_recall": 0.8454545454545455,
            "eval_micro_f1": 0.7793750000000002,
            "eval_macro_f1": 0.7778860330581665,
            "eval_macro_precision": 0.7803948521614075,
            "eval_macro_recall": 0.7892166376113892,
            "eval_acc": 0.779375,
            "eval_runtime": 3.3548,
            "eval_samples_per_second": 476.926,
            "eval_steps_per_second": 29.808,
            "epoch": 5.0
        },
        {
            "eval_loss": 1.0992213487625122,
            "eval_ok_f1": 0.7824540604623591,
            "eval_ok_precision": 0.8835341365461847,
            "eval_ok_recall": 0.7021276595744681,
            "eval_hateful_f1": 0.7574355584930602,
            "eval_hateful_precision": 0.671746776084408,
            "eval_hateful_recall": 0.8681818181818182,
            "eval_micro_f1": 0.770625,
            "eval_macro_f1": 0.7699447870254517,
            "eval_macro_precision": 0.7776404619216919,
            "eval_macro_recall": 0.7851547002792358,
            "eval_acc": 0.770625,
            "eval_runtime": 3.2747,
            "eval_samples_per_second": 488.589,
            "eval_steps_per_second": 30.537,
            "epoch": 5.0
        },
        {
            "eval_loss": 0.5603094696998596,
            "eval_ok_f1": 0.8265193370165747,
            "eval_ok_precision": 0.8597701149425288,
            "eval_ok_recall": 0.7957446808510639,
            "eval_hateful_f1": 0.7741007194244603,
            "eval_hateful_precision": 0.736986301369863,
            "eval_hateful_recall": 0.8151515151515152,
            "eval_micro_f1": 0.80375,
            "eval_macro_f1": 0.8003100156784058,
            "eval_macro_precision": 0.7983782291412354,
            "eval_macro_recall": 0.805448055267334,
            "eval_acc": 0.80375,
            "eval_runtime": 3.3429,
            "eval_samples_per_second": 478.629,
            "eval_steps_per_second": 29.914,
            "epoch": 5.0
        },
        {
            "eval_loss": 1.082260251045227,
            "eval_ok_f1": 0.8036322360953462,
            "eval_ok_precision": 0.8613138686131386,
            "eval_ok_recall": 0.7531914893617021,
            "eval_hateful_f1": 0.7593880389429764,
            "eval_hateful_precision": 0.7017994858611826,
            "eval_hateful_recall": 0.8272727272727273,
            "eval_micro_f1": 0.78375,
            "eval_macro_f1": 0.7815101146697998,
            "eval_macro_precision": 0.7815567255020142,
            "eval_macro_recall": 0.7902320623397827,
            "eval_acc": 0.78375,
            "eval_runtime": 3.1116,
            "eval_samples_per_second": 514.207,
            "eval_steps_per_second": 32.138,
            "epoch": 5.0
        },
        {
            "eval_loss": 1.0987122058868408,
            "eval_ok_f1": 0.8252911813643926,
            "eval_ok_precision": 0.8621089223638471,
            "eval_ok_recall": 0.7914893617021277,
            "eval_hateful_f1": 0.7745168217609163,
            "eval_hateful_precision": 0.7340569877883311,
            "eval_hateful_recall": 0.8196969696969697,
            "eval_micro_f1": 0.803125,
            "eval_macro_f1": 0.7999039888381958,
            "eval_macro_precision": 0.7980829477310181,
            "eval_macro_recall": 0.8055931329727173,
            "eval_acc": 0.803125,
            "eval_runtime": 3.0215,
            "eval_samples_per_second": 529.538,
            "eval_steps_per_second": 33.096,
            "epoch": 5.0
        },
        {
            "eval_loss": 1.0800789594650269,
            "eval_ok_f1": 0.8011494252873562,
            "eval_ok_precision": 0.87125,
            "eval_ok_recall": 0.7414893617021276,
            "eval_hateful_f1": 0.7630136986301371,
            "eval_hateful_precision": 0.69625,
            "eval_hateful_recall": 0.843939393939394,
            "eval_micro_f1": 0.78375,
            "eval_macro_f1": 0.7820816040039062,
            "eval_macro_precision": 0.7837499976158142,
            "eval_macro_recall": 0.7927143573760986,
            "eval_acc": 0.78375,
            "eval_runtime": 3.033,
            "eval_samples_per_second": 527.539,
            "eval_steps_per_second": 32.971,
            "epoch": 5.0
        },
        {
            "eval_loss": 1.1979527473449707,
            "eval_ok_f1": 0.7849588719153937,
            "eval_ok_precision": 0.8766404199475065,
            "eval_ok_recall": 0.7106382978723405,
            "eval_hateful_f1": 0.7556742323097464,
            "eval_hateful_precision": 0.6754176610978521,
            "eval_hateful_recall": 0.8575757575757575,
            "eval_micro_f1": 0.77125,
            "eval_macro_f1": 0.7703166007995605,
            "eval_macro_precision": 0.7760290503501892,
            "eval_macro_recall": 0.7841070294380188,
            "eval_acc": 0.77125,
            "eval_runtime": 3.0264,
            "eval_samples_per_second": 528.679,
            "eval_steps_per_second": 33.042,
            "epoch": 5.0
        },
        {
            "eval_loss": 1.103371262550354,
            "eval_ok_f1": 0.8050028425241615,
            "eval_ok_precision": 0.8644688644688645,
            "eval_ok_recall": 0.7531914893617021,
            "eval_hateful_f1": 0.761970853573907,
            "eval_hateful_precision": 0.7029449423815621,
            "eval_hateful_recall": 0.8318181818181818,
            "eval_micro_f1": 0.7856250000000001,
            "eval_macro_f1": 0.7834868431091309,
            "eval_macro_precision": 0.7837069034576416,
            "eval_macro_recall": 0.7925047874450684,
            "eval_acc": 0.785625,
            "eval_runtime": 3.0393,
            "eval_samples_per_second": 526.434,
            "eval_steps_per_second": 32.902,
            "epoch": 5.0
        },
        {
            "eval_loss": 0.5740035772323608,
            "eval_ok_f1": 0.8166761850371216,
            "eval_ok_precision": 0.8816276202219482,
            "eval_ok_recall": 0.7606382978723404,
            "eval_hateful_f1": 0.7784679089026916,
            "eval_hateful_precision": 0.714828897338403,
            "eval_hateful_recall": 0.8545454545454545,
            "eval_micro_f1": 0.799375,
            "eval_macro_f1": 0.7975720167160034,
            "eval_macro_precision": 0.7982282638549805,
            "eval_macro_recall": 0.8075919151306152,
            "eval_acc": 0.799375,
            "eval_runtime": 3.0307,
            "eval_samples_per_second": 527.936,
            "eval_steps_per_second": 32.996,
            "epoch": 5.0
        }
    ],
    "sentiment": [
        {
            "eval_loss": 1.5350160598754883,
            "eval_neg_f1": 0.7364228819695873,
            "eval_neg_precision": 0.7868471953578337,
            "eval_neg_recall": 0.6920721333787002,
            "eval_neu_f1": 0.5423881268270745,
            "eval_neu_precision": 0.4860943168077388,
            "eval_neu_recall": 0.6134282807731435,
            "eval_pos_f1": 0.7496159754224272,
            "eval_pos_precision": 0.7770700636942676,
            "eval_pos_recall": 0.7240356083086054,
            "eval_micro_f1": 0.6811674008810573,
            "eval_macro_f1": 0.6761422753334045,
            "eval_macro_precision": 0.6833372116088867,
            "eval_macro_recall": 0.6765120625495911,
            "eval_acc": 0.6811674008810573,
            "eval_runtime": 9.8508,
            "eval_samples_per_second": 737.4,
            "eval_steps_per_second": 46.087,
            "epoch": 5.0
        },
        {
            "eval_loss": 1.5351969003677368,
            "eval_neg_f1": 0.7474639615589962,
            "eval_neg_precision": 0.7835820895522388,
            "eval_neg_recall": 0.7145287512759442,
            "eval_neu_f1": 0.540235081374322,
            "eval_neu_precision": 0.4861676159479251,
            "eval_neu_recall": 0.6078331637843337,
            "eval_pos_f1": 0.7375696767001114,
            "eval_pos_precision": 0.7779868297271872,
            "eval_pos_recall": 0.7011445527766003,
            "eval_micro_f1": 0.6813050660792952,
            "eval_macro_f1": 0.6750895380973816,
            "eval_macro_precision": 0.6825788021087646,
            "eval_macro_recall": 0.6745021939277649,
            "eval_acc": 0.6813050660792952,
            "eval_runtime": 9.9056,
            "eval_samples_per_second": 733.322,
            "eval_steps_per_second": 45.833,
            "epoch": 5.0
        },
        {
            "eval_loss": 0.7846567034721375,
            "eval_neg_f1": 0.7532147260877223,
            "eval_neg_precision": 0.7808619430241052,
            "eval_neg_recall": 0.7274583191561755,
            "eval_neu_f1": 0.547945205479452,
            "eval_neu_precision": 0.5193621867881549,
            "eval_neu_recall": 0.5798575788402849,
            "eval_pos_f1": 0.7603411513859275,
            "eval_pos_precision": 0.7649077649077649,
            "eval_pos_recall": 0.7558287409919457,
            "eval_micro_f1": 0.6967235682819384,
            "eval_macro_f1": 0.6871669888496399,
            "eval_macro_precision": 0.688377320766449,
            "eval_macro_recall": 0.6877148747444153,
            "eval_acc": 0.6967235682819384,
            "eval_runtime": 10.1103,
            "eval_samples_per_second": 718.478,
            "eval_steps_per_second": 44.905,
            "epoch": 5.0
        },
        {
            "eval_loss": 1.0491561889648438,
            "eval_neg_f1": 0.7294799782569306,
            "eval_neg_precision": 0.7802325581395348,
            "eval_neg_recall": 0.6849268458659408,
            "eval_neu_f1": 0.5452229299363057,
            "eval_neu_precision": 0.4679300291545189,
            "eval_neu_recall": 0.6531027466937945,
            "eval_pos_f1": 0.729937194696441,
            "eval_pos_precision": 0.8087628865979382,
            "eval_pos_recall": 0.6651123357354811,
            "eval_micro_f1": 0.6698788546255506,
            "eval_macro_f1": 0.6682133674621582,
            "eval_macro_precision": 0.6856417655944824,
            "eval_macro_recall": 0.6677139401435852,
            "eval_acc": 0.6698788546255506,
            "eval_runtime": 9.9688,
            "eval_samples_per_second": 728.671,
            "eval_steps_per_second": 45.542,
            "epoch": 5.0
        },
        {
            "eval_loss": 1.5695158243179321,
            "eval_neg_f1": 0.7461212976022568,
            "eval_neg_precision": 0.774240761068423,
            "eval_neg_recall": 0.7199727798570943,
            "eval_neu_f1": 0.5399188092016238,
            "eval_neu_precision": 0.48500810372771475,
            "eval_neu_recall": 0.6088504577822991,
            "eval_pos_f1": 0.7376752600633197,
            "eval_pos_precision": 0.7905962190984004,
            "eval_pos_recall": 0.6913946587537092,
            "eval_micro_f1": 0.6806167400881057,
            "eval_macro_f1": 0.6745717525482178,
            "eval_macro_precision": 0.6832817196846008,
            "eval_macro_recall": 0.6734059453010559,
            "eval_acc": 0.6806167400881057,
            "eval_runtime": 9.8312,
            "eval_samples_per_second": 738.871,
            "eval_steps_per_second": 46.179,
            "epoch": 5.0
        },
        {
            "eval_loss": 0.8118229508399963,
            "eval_neg_f1": 0.7329125338142471,
            "eval_neg_precision": 0.7797390636991558,
            "eval_neg_recall": 0.6913916298060565,
            "eval_neu_f1": 0.5528562048588311,
            "eval_neu_precision": 0.48520937379946216,
            "eval_neu_recall": 0.6424211597151577,
            "eval_pos_f1": 0.7394653375623018,
            "eval_pos_precision": 0.7941605839416058,
            "eval_pos_recall": 0.6918185671894871,
            "eval_micro_f1": 0.6782764317180616,
            "eval_macro_f1": 0.6750780940055847,
            "eval_macro_precision": 0.6863697171211243,
            "eval_macro_recall": 0.6752104759216309,
            "eval_acc": 0.6782764317180616,
            "eval_runtime": 9.6143,
            "eval_samples_per_second": 755.545,
            "eval_steps_per_second": 47.222,
            "epoch": 5.0
        },
        {
            "eval_loss": 0.8038460612297058,
            "eval_neg_f1": 0.7423345884884346,
            "eval_neg_precision": 0.7846853677028052,
            "eval_neg_recall": 0.7043211976862879,
            "eval_neu_f1": 0.5576599326599326,
            "eval_neu_precision": 0.47559224694903085,
            "eval_neu_recall": 0.6739572736520855,
            "eval_pos_f1": 0.7216003810431055,
            "eval_pos_precision": 0.8233695652173914,
            "eval_pos_recall": 0.642221280203476,
            "eval_micro_f1": 0.6759361233480177,
            "eval_macro_f1": 0.6738649010658264,
            "eval_macro_precision": 0.6945490837097168,
            "eval_macro_recall": 0.6734998822212219,
            "eval_acc": 0.6759361233480177,
            "eval_runtime": 9.8369,
            "eval_samples_per_second": 738.446,
            "eval_steps_per_second": 46.153,
            "epoch": 5.0
        },
        {
            "eval_loss": 1.0472036600112915,
            "eval_neg_f1": 0.742467718794835,
            "eval_neg_precision": 0.7849829351535836,
            "eval_neg_recall": 0.7043211976862879,
            "eval_neu_f1": 0.5473090277777778,
            "eval_neu_precision": 0.4772899318697956,
            "eval_neu_recall": 0.6414038657171923,
            "eval_pos_f1": 0.7306629834254144,
            "eval_pos_precision": 0.7994962216624685,
            "eval_pos_recall": 0.6727426875794829,
            "eval_micro_f1": 0.6770374449339207,
            "eval_macro_f1": 0.6734799742698669,
            "eval_macro_precision": 0.6872563362121582,
            "eval_macro_recall": 0.6728225350379944,
            "eval_acc": 0.6770374449339207,
            "eval_runtime": 10.0033,
            "eval_samples_per_second": 726.16,
            "eval_steps_per_second": 45.385,
            "epoch": 5.0
        },
        {
            "eval_loss": 1.5255061388015747,
            "eval_neg_f1": 0.7411512334644261,
            "eval_neg_precision": 0.7807909604519774,
            "eval_neg_recall": 0.7053419530452535,
            "eval_neu_f1": 0.5467096180395766,
            "eval_neu_precision": 0.4991596638655462,
            "eval_neu_recall": 0.6042726347914548,
            "eval_pos_f1": 0.7428073234524848,
            "eval_pos_precision": 0.7644683714670256,
            "eval_pos_recall": 0.7223399745654938,
            "eval_micro_f1": 0.6835077092511013,
            "eval_macro_f1": 0.6768894195556641,
            "eval_macro_precision": 0.6814730167388916,
            "eval_macro_recall": 0.677318274974823,
            "eval_acc": 0.6835077092511013,
            "eval_runtime": 9.9687,
            "eval_samples_per_second": 728.679,
            "eval_steps_per_second": 45.542,
            "epoch": 5.0
        },
        {
            "eval_loss": 0.8119653463363647,
            "eval_neg_f1": 0.747047417592103,
            "eval_neg_precision": 0.7750548646671543,
            "eval_neg_recall": 0.7209935352160599,
            "eval_neu_f1": 0.5363835483085908,
            "eval_neu_precision": 0.5142323845076995,
            "eval_neu_recall": 0.560528992878942,
            "eval_pos_f1": 0.7475769068689424,
            "eval_pos_precision": 0.7431922915793884,
            "eval_pos_recall": 0.7520135650699449,
            "eval_micro_f1": 0.6876376651982379,
            "eval_macro_f1": 0.6770026683807373,
            "eval_macro_precision": 0.6774932742118835,
            "eval_macro_recall": 0.677845299243927,
            "eval_acc": 0.6876376651982379,
            "eval_runtime": 9.93,
            "eval_samples_per_second": 731.518,
            "eval_steps_per_second": 45.72,
            "epoch": 5.0
        },
        {
            "eval_loss": 1.5350160598754883,
            "eval_neg_f1": 0.7364228819695873,
            "eval_neg_precision": 0.7868471953578337,
            "eval_neg_recall": 0.6920721333787002,
            "eval_neu_f1": 0.5423881268270745,
            "eval_neu_precision": 0.4860943168077388,
            "eval_neu_recall": 0.6134282807731435,
            "eval_pos_f1": 0.7496159754224272,
            "eval_pos_precision": 0.7770700636942676,
            "eval_pos_recall": 0.7240356083086054,
            "eval_micro_f1": 0.6811674008810573,
            "eval_macro_f1": 0.6761422753334045,
            "eval_macro_precision": 0.6833372116088867,
            "eval_macro_recall": 0.6765120625495911,
            "eval_acc": 0.6811674008810573,
            "eval_runtime": 9.2551,
            "eval_samples_per_second": 784.862,
            "eval_steps_per_second": 49.054,
            "epoch": 5.0
        },
        {
            "eval_loss": 1.5351969003677368,
            "eval_neg_f1": 0.7474639615589962,
            "eval_neg_precision": 0.7835820895522388,
            "eval_neg_recall": 0.7145287512759442,
            "eval_neu_f1": 0.540235081374322,
            "eval_neu_precision": 0.4861676159479251,
            "eval_neu_recall": 0.6078331637843337,
            "eval_pos_f1": 0.7375696767001114,
            "eval_pos_precision": 0.7779868297271872,
            "eval_pos_recall": 0.7011445527766003,
            "eval_micro_f1": 0.6813050660792952,
            "eval_macro_f1": 0.6750895380973816,
            "eval_macro_precision": 0.6825788021087646,
            "eval_macro_recall": 0.6745021939277649,
            "eval_acc": 0.6813050660792952,
            "eval_runtime": 9.2644,
            "eval_samples_per_second": 784.077,
            "eval_steps_per_second": 49.005,
            "epoch": 5.0
        },
        {
            "eval_loss": 0.7846567034721375,
            "eval_neg_f1": 0.7532147260877223,
            "eval_neg_precision": 0.7808619430241052,
            "eval_neg_recall": 0.7274583191561755,
            "eval_neu_f1": 0.547945205479452,
            "eval_neu_precision": 0.5193621867881549,
            "eval_neu_recall": 0.5798575788402849,
            "eval_pos_f1": 0.7603411513859275,
            "eval_pos_precision": 0.7649077649077649,
            "eval_pos_recall": 0.7558287409919457,
            "eval_micro_f1": 0.6967235682819384,
            "eval_macro_f1": 0.6871669888496399,
            "eval_macro_precision": 0.688377320766449,
            "eval_macro_recall": 0.6877148747444153,
            "eval_acc": 0.6967235682819384,
            "eval_runtime": 9.2192,
            "eval_samples_per_second": 787.918,
            "eval_steps_per_second": 49.245,
            "epoch": 5.0
        },
        {
            "eval_loss": 1.0491561889648438,
            "eval_neg_f1": 0.7294799782569306,
            "eval_neg_precision": 0.7802325581395348,
            "eval_neg_recall": 0.6849268458659408,
            "eval_neu_f1": 0.5452229299363057,
            "eval_neu_precision": 0.4679300291545189,
            "eval_neu_recall": 0.6531027466937945,
            "eval_pos_f1": 0.729937194696441,
            "eval_pos_precision": 0.8087628865979382,
            "eval_pos_recall": 0.6651123357354811,
            "eval_micro_f1": 0.6698788546255506,
            "eval_macro_f1": 0.6682133674621582,
            "eval_macro_precision": 0.6856417655944824,
            "eval_macro_recall": 0.6677139401435852,
            "eval_acc": 0.6698788546255506,
            "eval_runtime": 9.2563,
            "eval_samples_per_second": 784.764,
            "eval_steps_per_second": 49.048,
            "epoch": 5.0
        },
        {
            "eval_loss": 1.5695158243179321,
            "eval_neg_f1": 0.7461212976022568,
            "eval_neg_precision": 0.774240761068423,
            "eval_neg_recall": 0.7199727798570943,
            "eval_neu_f1": 0.5399188092016238,
            "eval_neu_precision": 0.48500810372771475,
            "eval_neu_recall": 0.6088504577822991,
            "eval_pos_f1": 0.7376752600633197,
            "eval_pos_precision": 0.7905962190984004,
            "eval_pos_recall": 0.6913946587537092,
            "eval_micro_f1": 0.6806167400881057,
            "eval_macro_f1": 0.6745717525482178,
            "eval_macro_precision": 0.6832817196846008,
            "eval_macro_recall": 0.6734059453010559,
            "eval_acc": 0.6806167400881057,
            "eval_runtime": 9.2467,
            "eval_samples_per_second": 785.58,
            "eval_steps_per_second": 49.099,
            "epoch": 5.0
        }
    ],
    "emotion": [
        {
            "eval_loss": 1.5326205492019653,
            "eval_others_f1": 0.7318059299191374,
            "eval_others_precision": 0.8264840182648402,
            "eval_others_recall": 0.656590084643289,
            "eval_joy_f1": 0.6788990825688073,
            "eval_joy_precision": 0.6458852867830424,
            "eval_joy_recall": 0.7154696132596685,
            "eval_sadness_f1": 0.7482678983833718,
            "eval_sadness_precision": 0.6923076923076923,
            "eval_sadness_recall": 0.8140703517587939,
            "eval_anger_f1": 0.5495495495495496,
            "eval_anger_precision": 0.44525547445255476,
            "eval_anger_recall": 0.7176470588235294,
            "eval_surprise_f1": 0.3875968992248062,
            "eval_surprise_precision": 0.4098360655737705,
            "eval_surprise_recall": 0.36764705882352944,
            "eval_disgust_f1": 0.04,
            "eval_disgust_precision": 0.058823529411764705,
            "eval_disgust_recall": 0.030303030303030304,
            "eval_fear_f1": 0.5098039215686274,
            "eval_fear_precision": 0.3939393939393939,
            "eval_fear_recall": 0.7222222222222222,
            "eval_micro_f1": 0.6708407871198568,
            "eval_macro_f1": 0.5208461880683899,
            "eval_macro_precision": 0.49607592821121216,
            "eval_macro_recall": 0.5748499035835266,
            "eval_acc": 0.6708407871198568,
            "eval_runtime": 3.8167,
            "eval_samples_per_second": 439.381,
            "eval_steps_per_second": 27.51,
            "epoch": 5.0
        },
        {
            "eval_loss": 1.697834849357605,
            "eval_others_f1": 0.7697006719609041,
            "eval_others_precision": 0.7777777777777778,
            "eval_others_recall": 0.7617896009673518,
            "eval_joy_f1": 0.6790945406125166,
            "eval_joy_precision": 0.6555269922879178,
            "eval_joy_recall": 0.7044198895027625,
            "eval_sadness_f1": 0.7756097560975609,
            "eval_sadness_precision": 0.7535545023696683,
            "eval_sadness_recall": 0.7989949748743719,
            "eval_anger_f1": 0.5764705882352941,
            "eval_anger_precision": 0.5764705882352941,
            "eval_anger_recall": 0.5764705882352941,
            "eval_surprise_f1": 0.3636363636363637,
            "eval_surprise_precision": 0.47619047619047616,
            "eval_surprise_recall": 0.29411764705882354,
            "eval_disgust_f1": 0.03636363636363636,
            "eval_disgust_precision": 0.045454545454545456,
            "eval_disgust_recall": 0.030303030303030304,
            "eval_fear_f1": 0.5098039215686274,
            "eval_fear_precision": 0.3939393939393939,
            "eval_fear_recall": 0.7222222222222222,
            "eval_micro_f1": 0.7012522361359571,
            "eval_macro_f1": 0.5300970673561096,
            "eval_macro_precision": 0.5255591869354248,
            "eval_macro_recall": 0.5554739832878113,
            "eval_acc": 0.7012522361359571,
            "eval_runtime": 3.8262,
            "eval_samples_per_second": 438.299,
            "eval_steps_per_second": 27.443,
            "epoch": 5.0
        },
        {
            "eval_loss": 1.5352373123168945,
            "eval_others_f1": 0.7443708609271523,
            "eval_others_precision": 0.8228404099560761,
            "eval_others_recall": 0.6795646916565901,
            "eval_joy_f1": 0.6938271604938272,
            "eval_joy_precision": 0.6272321428571429,
            "eval_joy_recall": 0.7762430939226519,
            "eval_sadness_f1": 0.7481662591687042,
            "eval_sadness_precision": 0.7285714285714285,
            "eval_sadness_recall": 0.7688442211055276,
            "eval_anger_f1": 0.5685279187817259,
            "eval_anger_precision": 0.5,
            "eval_anger_recall": 0.6588235294117647,
            "eval_surprise_f1": 0.39344262295081966,
            "eval_surprise_precision": 0.4444444444444444,
            "eval_surprise_recall": 0.35294117647058826,
            "eval_disgust_f1": 0.14814814814814814,
            "eval_disgust_precision": 0.19047619047619047,
            "eval_disgust_recall": 0.12121212121212122,
            "eval_fear_f1": 0.4727272727272727,
            "eval_fear_precision": 0.35135135135135137,
            "eval_fear_recall": 0.7222222222222222,
            "eval_micro_f1": 0.6851520572450805,
            "eval_macro_f1": 0.5384586453437805,
            "eval_macro_precision": 0.5235594511032104,
            "eval_macro_recall": 0.582835853099823,
            "eval_acc": 0.6851520572450805,
            "eval_runtime": 3.6968,
            "eval_samples_per_second": 453.635,
            "eval_steps_per_second": 28.403,
            "epoch": 5.0
        },
        {
            "eval_loss": 1.2527179718017578,
            "eval_others_f1": 0.758364312267658,
            "eval_others_precision": 0.7776365946632783,
            "eval_others_recall": 0.7400241837968561,
            "eval_joy_f1": 0.6493860845839017,
            "eval_joy_precision": 0.6415094339622641,
            "eval_joy_recall": 0.6574585635359116,
            "eval_sadness_f1": 0.7700534759358288,
            "eval_sadness_precision": 0.8228571428571428,
            "eval_sadness_recall": 0.7236180904522613,
            "eval_anger_f1": 0.47382920110192833,
            "eval_anger_precision": 0.44559585492227977,
            "eval_anger_recall": 0.5058823529411764,
            "eval_surprise_f1": 0.37410071942446044,
            "eval_surprise_precision": 0.36619718309859156,
            "eval_surprise_recall": 0.38235294117647056,
            "eval_disgust_f1": 0.125,
            "eval_disgust_precision": 0.10638297872340426,
            "eval_disgust_recall": 0.15151515151515152,
            "eval_fear_f1": 0.5098039215686274,
            "eval_fear_precision": 0.3939393939393939,
            "eval_fear_recall": 0.7222222222222222,
            "eval_micro_f1": 0.6702444841979726,
            "eval_macro_f1": 0.5229339599609375,
            "eval_macro_precision": 0.5077312588691711,
            "eval_macro_recall": 0.5547247529029846,
            "eval_acc": 0.6702444841979726,
            "eval_runtime": 3.826,
            "eval_samples_per_second": 438.32,
            "eval_steps_per_second": 27.444,
            "epoch": 5.0
        },
        {
            "eval_loss": 1.7824320793151855,
            "eval_others_f1": 0.7708333333333334,
            "eval_others_precision": 0.7813664596273292,
            "eval_others_recall": 0.7605804111245466,
            "eval_joy_f1": 0.6851851851851852,
            "eval_joy_precision": 0.6573604060913706,
            "eval_joy_recall": 0.7154696132596685,
            "eval_sadness_f1": 0.7619047619047619,
            "eval_sadness_precision": 0.76,
            "eval_sadness_recall": 0.7638190954773869,
            "eval_anger_f1": 0.6153846153846153,
            "eval_anger_precision": 0.5773195876288659,
            "eval_anger_recall": 0.6588235294117647,
            "eval_surprise_f1": 0.3793103448275862,
            "eval_surprise_precision": 0.4583333333333333,
            "eval_surprise_recall": 0.3235294117647059,
            "eval_disgust_f1": 0.05,
            "eval_disgust_precision": 0.14285714285714285,
            "eval_disgust_recall": 0.030303030303030304,
            "eval_fear_f1": 0.5106382978723404,
            "eval_fear_precision": 0.41379310344827586,
            "eval_fear_recall": 0.6666666666666666,
            "eval_micro_f1": 0.7078115682766846,
            "eval_macro_f1": 0.5390366315841675,
            "eval_macro_precision": 0.5415757298469543,
            "eval_macro_recall": 0.5598845481872559,
            "eval_acc": 0.7078115682766846,
            "eval_runtime": 3.5768,
            "eval_samples_per_second": 468.851,
            "eval_steps_per_second": 29.356,
            "epoch": 5.0
        },
        {
            "eval_loss": 1.8031116724014282,
            "eval_others_f1": 0.7675276752767527,
            "eval_others_precision": 0.7809762202753442,
            "eval_others_recall": 0.75453446191052,
            "eval_joy_f1": 0.6849673202614379,
            "eval_joy_precision": 0.6501240694789082,
            "eval_joy_recall": 0.7237569060773481,
            "eval_sadness_f1": 0.7563451776649746,
            "eval_sadness_precision": 0.764102564102564,
            "eval_sadness_recall": 0.7487437185929648,
            "eval_anger_f1": 0.5810055865921787,
            "eval_anger_precision": 0.5531914893617021,
            "eval_anger_recall": 0.611764705882353,
            "eval_surprise_f1": 0.3684210526315789,
            "eval_surprise_precision": 0.45652173913043476,
            "eval_surprise_recall": 0.3088235294117647,
            "eval_disgust_f1": 0.0392156862745098,
            "eval_disgust_precision": 0.05555555555555555,
            "eval_disgust_recall": 0.030303030303030304,
            "eval_fear_f1": 0.5217391304347826,
            "eval_fear_precision": 0.42857142857142855,
            "eval_fear_recall": 0.6666666666666666,
            "eval_micro_f1": 0.6994633273703041,
            "eval_macro_f1": 0.5313173532485962,
            "eval_macro_precision": 0.527006208896637,
            "eval_macro_recall": 0.5492275953292847,
            "eval_acc": 0.6994633273703041,
            "eval_runtime": 3.8077,
            "eval_samples_per_second": 440.425,
            "eval_steps_per_second": 27.576,
            "epoch": 5.0
        },
        {
            "eval_loss": 1.7076010704040527,
            "eval_others_f1": 0.7658779576587796,
            "eval_others_precision": 0.7894736842105263,
            "eval_others_recall": 0.7436517533252721,
            "eval_joy_f1": 0.6917098445595854,
            "eval_joy_precision": 0.651219512195122,
            "eval_joy_recall": 0.7375690607734806,
            "eval_sadness_f1": 0.7391304347826086,
            "eval_sadness_precision": 0.7116279069767442,
            "eval_sadness_recall": 0.7688442211055276,
            "eval_anger_f1": 0.6111111111111113,
            "eval_anger_precision": 0.5789473684210527,
            "eval_anger_recall": 0.6470588235294118,
            "eval_surprise_f1": 0.34862385321100914,
            "eval_surprise_precision": 0.4634146341463415,
            "eval_surprise_recall": 0.27941176470588236,
            "eval_disgust_f1": 0.043478260869565216,
            "eval_disgust_precision": 0.07692307692307693,
            "eval_disgust_recall": 0.030303030303030304,
            "eval_fear_f1": 0.5531914893617021,
            "eval_fear_precision": 0.4482758620689655,
            "eval_fear_recall": 0.7222222222222222,
            "eval_micro_f1": 0.7024448419797257,
            "eval_macro_f1": 0.536160409450531,
            "eval_macro_precision": 0.5314117670059204,
            "eval_macro_recall": 0.561294436454773,
            "eval_acc": 0.7024448419797257,
            "eval_runtime": 3.5635,
            "eval_samples_per_second": 470.603,
            "eval_steps_per_second": 29.465,
            "epoch": 5.0
        },
        {
            "eval_loss": 1.7695268392562866,
            "eval_others_f1": 0.7662740235585864,
            "eval_others_precision": 0.7862595419847328,
            "eval_others_recall": 0.747279322853688,
            "eval_joy_f1": 0.6752577319587629,
            "eval_joy_precision": 0.6328502415458938,
            "eval_joy_recall": 0.7237569060773481,
            "eval_sadness_f1": 0.7808564231738035,
            "eval_sadness_precision": 0.7828282828282829,
            "eval_sadness_recall": 0.7788944723618091,
            "eval_anger_f1": 0.6077348066298343,
            "eval_anger_precision": 0.5729166666666666,
            "eval_anger_recall": 0.6470588235294118,
            "eval_surprise_f1": 0.3728813559322034,
            "eval_surprise_precision": 0.44,
            "eval_surprise_recall": 0.3235294117647059,
            "eval_disgust_f1": 0.04651162790697675,
            "eval_disgust_precision": 0.1,
            "eval_disgust_recall": 0.030303030303030304,
            "eval_fear_f1": 0.5777777777777777,
            "eval_fear_precision": 0.48148148148148145,
            "eval_fear_recall": 0.7222222222222222,
            "eval_micro_f1": 0.7042337507453786,
            "eval_macro_f1": 0.5467562675476074,
            "eval_macro_precision": 0.542333722114563,
            "eval_macro_recall": 0.5675777792930603,
            "eval_acc": 0.7042337507453786,
            "eval_runtime": 3.5644,
            "eval_samples_per_second": 470.484,
            "eval_steps_per_second": 29.458,
            "epoch": 5.0
        },
        {
            "eval_loss": 1.527833104133606,
            "eval_others_f1": 0.7330195023537323,
            "eval_others_precision": 0.8257575757575758,
            "eval_others_recall": 0.6590084643288996,
            "eval_joy_f1": 0.6862026862026862,
            "eval_joy_precision": 0.6148796498905909,
            "eval_joy_recall": 0.7762430939226519,
            "eval_sadness_f1": 0.7751937984496123,
            "eval_sadness_precision": 0.7978723404255319,
            "eval_sadness_recall": 0.7537688442211056,
            "eval_anger_f1": 0.5552941176470588,
            "eval_anger_precision": 0.4627450980392157,
            "eval_anger_recall": 0.6941176470588235,
            "eval_surprise_f1": 0.35211267605633806,
            "eval_surprise_precision": 0.33783783783783783,
            "eval_surprise_recall": 0.36764705882352944,
            "eval_disgust_f1": 0.0392156862745098,
            "eval_disgust_precision": 0.05555555555555555,
            "eval_disgust_recall": 0.030303030303030304,
            "eval_fear_f1": 0.6046511627906976,
            "eval_fear_precision": 0.52,
            "eval_fear_recall": 0.7222222222222222,
            "eval_micro_f1": 0.6756112104949314,
            "eval_macro_f1": 0.5350985527038574,
            "eval_macro_precision": 0.5163782835006714,
            "eval_macro_recall": 0.5719014406204224,
            "eval_acc": 0.6756112104949314,
            "eval_runtime": 3.8185,
            "eval_samples_per_second": 439.172,
            "eval_steps_per_second": 27.497,
            "epoch": 5.0
        },
        {
            "eval_loss": 1.8001313209533691,
            "eval_others_f1": 0.7697841726618705,
            "eval_others_precision": 0.7633769322235434,
            "eval_others_recall": 0.7762998790810157,
            "eval_joy_f1": 0.6648275862068965,
            "eval_joy_precision": 0.6639118457300276,
            "eval_joy_recall": 0.6657458563535912,
            "eval_sadness_f1": 0.7692307692307694,
            "eval_sadness_precision": 0.7853403141361257,
            "eval_sadness_recall": 0.7537688442211056,
            "eval_anger_f1": 0.6190476190476191,
            "eval_anger_precision": 0.5625,
            "eval_anger_recall": 0.6882352941176471,
            "eval_surprise_f1": 0.37037037037037035,
            "eval_surprise_precision": 0.5,
            "eval_surprise_recall": 0.29411764705882354,
            "eval_disgust_f1": 0.05128205128205128,
            "eval_disgust_precision": 0.16666666666666666,
            "eval_disgust_recall": 0.030303030303030304,
            "eval_fear_f1": 0.5652173913043479,
            "eval_fear_precision": 0.4642857142857143,
            "eval_fear_recall": 0.7222222222222222,
            "eval_micro_f1": 0.7060226595110316,
            "eval_macro_f1": 0.5442514419555664,
            "eval_macro_precision": 0.5580116510391235,
            "eval_macro_recall": 0.5615275502204895,
            "eval_acc": 0.7060226595110316,
            "eval_runtime": 3.8199,
            "eval_samples_per_second": 439.014,
            "eval_steps_per_second": 27.487,
            "epoch": 5.0
        },
        {
            "eval_loss": 1.5326205492019653,
            "eval_others_f1": 0.7318059299191374,
            "eval_others_precision": 0.8264840182648402,
            "eval_others_recall": 0.656590084643289,
            "eval_joy_f1": 0.6788990825688073,
            "eval_joy_precision": 0.6458852867830424,
            "eval_joy_recall": 0.7154696132596685,
            "eval_sadness_f1": 0.7482678983833718,
            "eval_sadness_precision": 0.6923076923076923,
            "eval_sadness_recall": 0.8140703517587939,
            "eval_anger_f1": 0.5495495495495496,
            "eval_anger_precision": 0.44525547445255476,
            "eval_anger_recall": 0.7176470588235294,
            "eval_surprise_f1": 0.3875968992248062,
            "eval_surprise_precision": 0.4098360655737705,
            "eval_surprise_recall": 0.36764705882352944,
            "eval_disgust_f1": 0.04,
            "eval_disgust_precision": 0.058823529411764705,
            "eval_disgust_recall": 0.030303030303030304,
            "eval_fear_f1": 0.5098039215686274,
            "eval_fear_precision": 0.3939393939393939,
            "eval_fear_recall": 0.7222222222222222,
            "eval_micro_f1": 0.6708407871198568,
            "eval_macro_f1": 0.5208461880683899,
            "eval_macro_precision": 0.49607592821121216,
            "eval_macro_recall": 0.5748499035835266,
            "eval_acc": 0.6708407871198568,
            "eval_runtime": 3.4794,
            "eval_samples_per_second": 481.985,
            "eval_steps_per_second": 30.178,
            "epoch": 5.0
        },
        {
            "eval_loss": 1.697834849357605,
            "eval_others_f1": 0.7697006719609041,
            "eval_others_precision": 0.7777777777777778,
            "eval_others_recall": 0.7617896009673518,
            "eval_joy_f1": 0.6790945406125166,
            "eval_joy_precision": 0.6555269922879178,
            "eval_joy_recall": 0.7044198895027625,
            "eval_sadness_f1": 0.7756097560975609,
            "eval_sadness_precision": 0.7535545023696683,
            "eval_sadness_recall": 0.7989949748743719,
            "eval_anger_f1": 0.5764705882352941,
            "eval_anger_precision": 0.5764705882352941,
            "eval_anger_recall": 0.5764705882352941,
            "eval_surprise_f1": 0.3636363636363637,
            "eval_surprise_precision": 0.47619047619047616,
            "eval_surprise_recall": 0.29411764705882354,
            "eval_disgust_f1": 0.03636363636363636,
            "eval_disgust_precision": 0.045454545454545456,
            "eval_disgust_recall": 0.030303030303030304,
            "eval_fear_f1": 0.5098039215686274,
            "eval_fear_precision": 0.3939393939393939,
            "eval_fear_recall": 0.7222222222222222,
            "eval_micro_f1": 0.7012522361359571,
            "eval_macro_f1": 0.5300970673561096,
            "eval_macro_precision": 0.5255591869354248,
            "eval_macro_recall": 0.5554739832878113,
            "eval_acc": 0.7012522361359571,
            "eval_runtime": 3.4822,
            "eval_samples_per_second": 481.588,
            "eval_steps_per_second": 30.153,
            "epoch": 5.0
        },
        {
            "eval_loss": 1.5352373123168945,
            "eval_others_f1": 0.7443708609271523,
            "eval_others_precision": 0.8228404099560761,
            "eval_others_recall": 0.6795646916565901,
            "eval_joy_f1": 0.6938271604938272,
            "eval_joy_precision": 0.6272321428571429,
            "eval_joy_recall": 0.7762430939226519,
            "eval_sadness_f1": 0.7481662591687042,
            "eval_sadness_precision": 0.7285714285714285,
            "eval_sadness_recall": 0.7688442211055276,
            "eval_anger_f1": 0.5685279187817259,
            "eval_anger_precision": 0.5,
            "eval_anger_recall": 0.6588235294117647,
            "eval_surprise_f1": 0.39344262295081966,
            "eval_surprise_precision": 0.4444444444444444,
            "eval_surprise_recall": 0.35294117647058826,
            "eval_disgust_f1": 0.14814814814814814,
            "eval_disgust_precision": 0.19047619047619047,
            "eval_disgust_recall": 0.12121212121212122,
            "eval_fear_f1": 0.4727272727272727,
            "eval_fear_precision": 0.35135135135135137,
            "eval_fear_recall": 0.7222222222222222,
            "eval_micro_f1": 0.6851520572450805,
            "eval_macro_f1": 0.5384586453437805,
            "eval_macro_precision": 0.5235594511032104,
            "eval_macro_recall": 0.582835853099823,
            "eval_acc": 0.6851520572450805,
            "eval_runtime": 3.4876,
            "eval_samples_per_second": 480.846,
            "eval_steps_per_second": 30.107,
            "epoch": 5.0
        },
        {
            "eval_loss": 1.2527179718017578,
            "eval_others_f1": 0.758364312267658,
            "eval_others_precision": 0.7776365946632783,
            "eval_others_recall": 0.7400241837968561,
            "eval_joy_f1": 0.6493860845839017,
            "eval_joy_precision": 0.6415094339622641,
            "eval_joy_recall": 0.6574585635359116,
            "eval_sadness_f1": 0.7700534759358288,
            "eval_sadness_precision": 0.8228571428571428,
            "eval_sadness_recall": 0.7236180904522613,
            "eval_anger_f1": 0.47382920110192833,
            "eval_anger_precision": 0.44559585492227977,
            "eval_anger_recall": 0.5058823529411764,
            "eval_surprise_f1": 0.37410071942446044,
            "eval_surprise_precision": 0.36619718309859156,
            "eval_surprise_recall": 0.38235294117647056,
            "eval_disgust_f1": 0.125,
            "eval_disgust_precision": 0.10638297872340426,
            "eval_disgust_recall": 0.15151515151515152,
            "eval_fear_f1": 0.5098039215686274,
            "eval_fear_precision": 0.3939393939393939,
            "eval_fear_recall": 0.7222222222222222,
            "eval_micro_f1": 0.6702444841979726,
            "eval_macro_f1": 0.5229339599609375,
            "eval_macro_precision": 0.5077312588691711,
            "eval_macro_recall": 0.5547247529029846,
            "eval_acc": 0.6702444841979726,
            "eval_runtime": 3.4833,
            "eval_samples_per_second": 481.44,
            "eval_steps_per_second": 30.144,
            "epoch": 5.0
        },
        {
            "eval_loss": 1.7824320793151855,
            "eval_others_f1": 0.7708333333333334,
            "eval_others_precision": 0.7813664596273292,
            "eval_others_recall": 0.7605804111245466,
            "eval_joy_f1": 0.6851851851851852,
            "eval_joy_precision": 0.6573604060913706,
            "eval_joy_recall": 0.7154696132596685,
            "eval_sadness_f1": 0.7619047619047619,
            "eval_sadness_precision": 0.76,
            "eval_sadness_recall": 0.7638190954773869,
            "eval_anger_f1": 0.6153846153846153,
            "eval_anger_precision": 0.5773195876288659,
            "eval_anger_recall": 0.6588235294117647,
            "eval_surprise_f1": 0.3793103448275862,
            "eval_surprise_precision": 0.4583333333333333,
            "eval_surprise_recall": 0.3235294117647059,
            "eval_disgust_f1": 0.05,
            "eval_disgust_precision": 0.14285714285714285,
            "eval_disgust_recall": 0.030303030303030304,
            "eval_fear_f1": 0.5106382978723404,
            "eval_fear_precision": 0.41379310344827586,
            "eval_fear_recall": 0.6666666666666666,
            "eval_micro_f1": 0.7078115682766846,
            "eval_macro_f1": 0.5390366315841675,
            "eval_macro_precision": 0.5415757298469543,
            "eval_macro_recall": 0.5598845481872559,
            "eval_acc": 0.7078115682766846,
            "eval_runtime": 3.4793,
            "eval_samples_per_second": 481.992,
            "eval_steps_per_second": 30.178,
            "epoch": 5.0
        }
    ],
    "irony": [
        {
            "eval_loss": 1.4357153177261353,
            "eval_not ironic_f1": 0.8155654641264694,
            "eval_not ironic_precision": 0.7946287519747235,
            "eval_not ironic_recall": 0.8376353039134055,
            "eval_ironic_f1": 0.5984112974404237,
            "eval_ironic_precision": 0.6348314606741573,
            "eval_ironic_recall": 0.5659432387312187,
            "eval_micro_f1": 0.7472222222222223,
            "eval_macro_f1": 0.7069883942604065,
            "eval_macro_precision": 0.7147301435470581,
            "eval_macro_recall": 0.7017892599105835,
            "eval_acc": 0.7472222222222222,
            "eval_runtime": 4.3931,
            "eval_samples_per_second": 409.735,
            "eval_steps_per_second": 25.722,
            "epoch": 5.0
        },
        {
            "eval_loss": 0.9417686462402344,
            "eval_not ironic_f1": 0.8230647709320694,
            "eval_not ironic_precision": 0.782870022539444,
            "eval_not ironic_recall": 0.8676103247293921,
            "eval_ironic_f1": 0.5805243445692884,
            "eval_ironic_precision": 0.6609808102345416,
            "eval_ironic_recall": 0.5175292153589316,
            "eval_micro_f1": 0.7511111111111111,
            "eval_macro_f1": 0.7017945051193237,
            "eval_macro_precision": 0.7219253778457642,
            "eval_macro_recall": 0.6925697326660156,
            "eval_acc": 0.7511111111111111,
            "eval_runtime": 4.4862,
            "eval_samples_per_second": 401.232,
            "eval_steps_per_second": 25.188,
            "epoch": 5.0
        },
        {
            "eval_loss": 0.5692000389099121,
            "eval_not ironic_f1": 0.8211974110032362,
            "eval_not ironic_precision": 0.7985837922895358,
            "eval_not ironic_recall": 0.8451290591174022,
            "eval_ironic_f1": 0.6081560283687943,
            "eval_ironic_precision": 0.6483931947069943,
            "eval_ironic_recall": 0.5726210350584308,
            "eval_micro_f1": 0.7544444444444445,
            "eval_macro_f1": 0.7146767377853394,
            "eval_macro_precision": 0.7234885096549988,
            "eval_macro_recall": 0.7088750600814819,
            "eval_acc": 0.7544444444444445,
            "eval_runtime": 4.4719,
            "eval_samples_per_second": 402.512,
            "eval_steps_per_second": 25.269,
            "epoch": 5.0
        },
        {
            "eval_loss": 0.5664833188056946,
            "eval_not ironic_f1": 0.7994746059544658,
            "eval_not ironic_precision": 0.8430286241920592,
            "eval_not ironic_recall": 0.7601998334721066,
            "eval_ironic_f1": 0.6519756838905775,
            "eval_ironic_precision": 0.5983263598326359,
            "eval_ironic_recall": 0.7161936560934892,
            "eval_micro_f1": 0.7455555555555555,
            "eval_macro_f1": 0.7257251739501953,
            "eval_macro_precision": 0.7206774950027466,
            "eval_macro_recall": 0.7381967306137085,
            "eval_acc": 0.7455555555555555,
            "eval_runtime": 4.2273,
            "eval_samples_per_second": 425.802,
            "eval_steps_per_second": 26.731,
            "epoch": 5.0
        },
        {
            "eval_loss": 0.5565406680107117,
            "eval_not ironic_f1": 0.8290360967869893,
            "eval_not ironic_precision": 0.7916666666666666,
            "eval_not ironic_recall": 0.8701082431307244,
            "eval_ironic_f1": 0.6005560704355886,
            "eval_ironic_precision": 0.675,
            "eval_ironic_recall": 0.5409015025041736,
            "eval_micro_f1": 0.7605555555555555,
            "eval_macro_f1": 0.7147960662841797,
            "eval_macro_precision": 0.7333333492279053,
            "eval_macro_recall": 0.7055048942565918,
            "eval_acc": 0.7605555555555555,
            "eval_runtime": 4.4747,
            "eval_samples_per_second": 402.261,
            "eval_steps_per_second": 25.253,
            "epoch": 5.0
        },
        {
            "eval_loss": 0.6069002151489258,
            "eval_not ironic_f1": 0.8186314921681782,
            "eval_not ironic_precision": 0.8106122448979591,
            "eval_not ironic_recall": 0.8268109908409659,
            "eval_ironic_f1": 0.6252129471890971,
            "eval_ironic_precision": 0.6382608695652174,
            "eval_ironic_recall": 0.6126878130217028,
            "eval_micro_f1": 0.7555555555555555,
            "eval_macro_f1": 0.7219222187995911,
            "eval_macro_precision": 0.7244365215301514,
            "eval_macro_recall": 0.7197494506835938,
            "eval_acc": 0.7555555555555555,
            "eval_runtime": 4.1337,
            "eval_samples_per_second": 435.442,
            "eval_steps_per_second": 27.336,
            "epoch": 5.0
        },
        {
            "eval_loss": 0.9082839488983154,
            "eval_not ironic_f1": 0.7986171132238549,
            "eval_not ironic_precision": 0.8301886792452831,
            "eval_not ironic_recall": 0.7693588676103247,
            "eval_ironic_f1": 0.6376360808709176,
            "eval_ironic_precision": 0.5967976710334789,
            "eval_ironic_recall": 0.6844741235392321,
            "eval_micro_f1": 0.7411111111111112,
            "eval_macro_f1": 0.7181265950202942,
            "eval_macro_precision": 0.7134931683540344,
            "eval_macro_recall": 0.726916491985321,
            "eval_acc": 0.7411111111111112,
            "eval_runtime": 4.2455,
            "eval_samples_per_second": 423.982,
            "eval_steps_per_second": 26.617,
            "epoch": 5.0
        },
        {
            "eval_loss": 0.5455825924873352,
            "eval_not ironic_f1": 0.8221056877773296,
            "eval_not ironic_precision": 0.797339593114241,
            "eval_not ironic_recall": 0.8484596169858452,
            "eval_ironic_f1": 0.6066012488849241,
            "eval_ironic_precision": 0.6513409961685823,
            "eval_ironic_recall": 0.5676126878130217,
            "eval_micro_f1": 0.755,
            "eval_macro_f1": 0.7143534421920776,
            "eval_macro_precision": 0.7243403196334839,
            "eval_macro_recall": 0.7080361843109131,
            "eval_acc": 0.755,
            "eval_runtime": 4.4255,
            "eval_samples_per_second": 406.729,
            "eval_steps_per_second": 25.534,
            "epoch": 5.0
        },
        {
            "eval_loss": 1.1830875873565674,
            "eval_not ironic_f1": 0.8260695721711315,
            "eval_not ironic_precision": 0.7946153846153846,
            "eval_not ironic_recall": 0.8601165695253955,
            "eval_ironic_f1": 0.6041856232939036,
            "eval_ironic_precision": 0.664,
            "eval_ironic_recall": 0.5542570951585977,
            "eval_micro_f1": 0.7583333333333333,
            "eval_macro_f1": 0.7151275873184204,
            "eval_macro_precision": 0.7293076515197754,
            "eval_macro_recall": 0.7071868181228638,
            "eval_acc": 0.7583333333333333,
            "eval_runtime": 4.29,
            "eval_samples_per_second": 419.576,
            "eval_steps_per_second": 26.34,
            "epoch": 5.0
        },
        {
            "eval_loss": 1.1141592264175415,
            "eval_not ironic_f1": 0.8111298482293423,
            "eval_not ironic_precision": 0.8215200683176772,
            "eval_not ironic_recall": 0.8009991673605329,
            "eval_ironic_f1": 0.6351791530944626,
            "eval_ironic_precision": 0.6200317965023847,
            "eval_ironic_recall": 0.6510851419031719,
            "eval_micro_f1": 0.7511111111111111,
            "eval_macro_f1": 0.7231545448303223,
            "eval_macro_precision": 0.7207759618759155,
            "eval_macro_recall": 0.7260421514511108,
            "eval_acc": 0.7511111111111111,
            "eval_runtime": 4.1662,
            "eval_samples_per_second": 432.047,
            "eval_steps_per_second": 27.123,
            "epoch": 5.0
        },
        {
            "eval_loss": 1.4357153177261353,
            "eval_not ironic_f1": 0.8155654641264694,
            "eval_not ironic_precision": 0.7946287519747235,
            "eval_not ironic_recall": 0.8376353039134055,
            "eval_ironic_f1": 0.5984112974404237,
            "eval_ironic_precision": 0.6348314606741573,
            "eval_ironic_recall": 0.5659432387312187,
            "eval_micro_f1": 0.7472222222222223,
            "eval_macro_f1": 0.7069883942604065,
            "eval_macro_precision": 0.7147301435470581,
            "eval_macro_recall": 0.7017892599105835,
            "eval_acc": 0.7472222222222222,
            "eval_runtime": 4.069,
            "eval_samples_per_second": 442.364,
            "eval_steps_per_second": 27.771,
            "epoch": 5.0
        },
        {
            "eval_loss": 0.9417686462402344,
            "eval_not ironic_f1": 0.8230647709320694,
            "eval_not ironic_precision": 0.782870022539444,
            "eval_not ironic_recall": 0.8676103247293921,
            "eval_ironic_f1": 0.5805243445692884,
            "eval_ironic_precision": 0.6609808102345416,
            "eval_ironic_recall": 0.5175292153589316,
            "eval_micro_f1": 0.7511111111111111,
            "eval_macro_f1": 0.7017945051193237,
            "eval_macro_precision": 0.7219253778457642,
            "eval_macro_recall": 0.6925697326660156,
            "eval_acc": 0.7511111111111111,
            "eval_runtime": 4.0748,
            "eval_samples_per_second": 441.739,
            "eval_steps_per_second": 27.731,
            "epoch": 5.0
        },
        {
            "eval_loss": 0.5692000389099121,
            "eval_not ironic_f1": 0.8211974110032362,
            "eval_not ironic_precision": 0.7985837922895358,
            "eval_not ironic_recall": 0.8451290591174022,
            "eval_ironic_f1": 0.6081560283687943,
            "eval_ironic_precision": 0.6483931947069943,
            "eval_ironic_recall": 0.5726210350584308,
            "eval_micro_f1": 0.7544444444444445,
            "eval_macro_f1": 0.7146767377853394,
            "eval_macro_precision": 0.7234885096549988,
            "eval_macro_recall": 0.7088750600814819,
            "eval_acc": 0.7544444444444445,
            "eval_runtime": 4.0686,
            "eval_samples_per_second": 442.417,
            "eval_steps_per_second": 27.774,
            "epoch": 5.0
        },
        {
            "eval_loss": 0.5664833188056946,
            "eval_not ironic_f1": 0.7994746059544658,
            "eval_not ironic_precision": 0.8430286241920592,
            "eval_not ironic_recall": 0.7601998334721066,
            "eval_ironic_f1": 0.6519756838905775,
            "eval_ironic_precision": 0.5983263598326359,
            "eval_ironic_recall": 0.7161936560934892,
            "eval_micro_f1": 0.7455555555555555,
            "eval_macro_f1": 0.7257251739501953,
            "eval_macro_precision": 0.7206774950027466,
            "eval_macro_recall": 0.7381967306137085,
            "eval_acc": 0.7455555555555555,
            "eval_runtime": 4.0618,
            "eval_samples_per_second": 443.152,
            "eval_steps_per_second": 27.82,
            "epoch": 5.0
        },
        {
            "eval_loss": 0.5565406680107117,
            "eval_not ironic_f1": 0.8290360967869893,
            "eval_not ironic_precision": 0.7916666666666666,
            "eval_not ironic_recall": 0.8701082431307244,
            "eval_ironic_f1": 0.6005560704355886,
            "eval_ironic_precision": 0.675,
            "eval_ironic_recall": 0.5409015025041736,
            "eval_micro_f1": 0.7605555555555555,
            "eval_macro_f1": 0.7147960662841797,
            "eval_macro_precision": 0.7333333492279053,
            "eval_macro_recall": 0.7055048942565918,
            "eval_acc": 0.7605555555555555,
            "eval_runtime": 4.067,
            "eval_samples_per_second": 442.586,
            "eval_steps_per_second": 27.785,
            "epoch": 5.0
        }
    ],
    "model_name": "models/beto-uncased-2500"
}